Workbook

Sheet Comparaison versions
B2: PROJET LOGICIEL PME — COMPARAISON
B3: Solo TA vs Compagnie Solo
B4: État d'avancement de chaque version du logiciel
B6: ▌ VERSION TRAVAILLEUR AUTONOME | F6: ▌ VERSION COMPAGNIE SOLO
B9: =AVERAGEIF(Modules!H5:H36,"✓ Oui",Modules!D5:D36) -> 0.918 | F9: =AVERAGEIF(Modules!I5:I36,"✓ Oui",Modules!D5:D36) -> 0.775
B10: Avancement moyen | F10: Avancement moyen
B13: =COUNTIF(Modules!H5:H36,"✓ Oui") -> 25 | C13: =COUNTIFS(Modules!H5:H36,"✓ Oui",Modules!D5:D36,1) -> 12 | D13: =SUMIF(Modules!H5:H36,"✓ Oui",Modules!F5:F36)&" j" -> 4,4 j | F13: =COUNTIF(Modules!I5:I36,"✓ Oui") -> 32 | G13: =COUNTIFS(Modules!I5:I36,"✓ Oui",Modules!D5:D36,1) -> 12 | H13: =SUMIF(Modules!I5:I36,"✓ Oui",Modules!F5:F36)&" j" -> 19,475 j
B14: Modules | C14: Complétés | D14: Effort | F14: Modules | G14: Complétés | H14: Effort
B16: Répartition par état | F16: Répartition par état
B17: Complétés | D17: =COUNTIFS(Modules!H5:H36,"✓ Oui",Modules!D5:D36,1) -> 12 | F17: Complétés | H17: =COUNTIFS(Modules!I5:I36,"✓ Oui",Modules!D5:D36,1) -> 12
B18: En cours | D18: =COUNTIFS(Modules!H5:H36,"✓ Oui",Modules!D5:D36,">0",Modules!D5:D36,"<1") -> 13 | F18: En cours | H18: =COUNTIFS(Modules!I5:I36,"✓ Oui",Modules!D5:D36,">0",Modules!D5:D36,"<1") -> 15
B19: Non commencés | D19: =COUNTIFS(Modules!H5:H36,"✓ Oui",Modules!D5:D36,0) -> 0 | F19: Non commencés | H19: =COUNTIFS(Modules!I5:I36,"✓ Oui",Modules!D5:D36,0) -> 5
B21: 💡 La version Solo TA est plus avancée car elle exclut les modules les plus lourds (paie, DAS, rapprochement bancaire, amortissement).
B22: 📋 Consultez les onglets « Solo TA », « Compagnie » et « Modules » pour le détail.

Sheet Solo TA
B2: VERSION TRAVAILLEUR AUTONOME
B3: Solo TA — Modules inclus
B4: Liste filtrée des modules de la version solo
B6: # | C6: Module | D6: Avancement | E6: PreProd Avancement | F6: Effort | G6: Effort initial | H6: Statut
B7: 1 | C7: Gestion des clients (CRUD) | D7: =IFERROR(VLOOKUP(C7,Modules!$C$5:$G$36,2,FALSE()),0) -> 0.9 | E7: =IFERROR(VLOOKUP(C7,Modules!$C$5:$G$36,3,FALSE()),0) -> 0 | F7: =IFERROR(VLOOKUP(C7,Modules!$C$5:$G$36,3,FALSE()),0) -> 0 | G7: =IFERROR(VLOOKUP(C7,Modules!$C$5:$G$36,4,FALSE()),0) -> 0.05 | H7: =IF(D7=1,"Complété",IF(D7=0,"À faire","En cours")) -> En cours
B8: 2 | C8: Facturation client | D8: =IFERROR(VLOOKUP(C8,Modules!$C$5:$G$36,2,FALSE()),0) -> 1 | E8: =IFERROR(VLOOKUP(C8,Modules!$C$5:$G$36,3,FALSE()),0) -> 0 | F8: =IFERROR(VLOOKUP(C8,Modules!$C$5:$G$36,3,FALSE()),0) -> 0 | G8: =IFERROR(VLOOKUP(C8,Modules!$C$5:$G$36,4,FALSE()),0) -> 0 | H8: =IF(D8=1,"Complété",IF(D8=0,"À faire","En cours")) -> Complété
B9: 3 | C9: Gestion des fournisseurs | D9: =IFERROR(VLOOKUP(C9,Modules!$C$5:$G$36,2,FALSE()),0) -> 0.9 | E9: =IFERROR(VLOOKUP(C9,Modules!$C$5:$G$36,3,FALSE()),0) -> 0 | F9: =IFERROR(VLOOKUP(C9,Modules!$C$5:$G$36,3,FALSE()),0) -> 0 | G9: =IFERROR(VLOOKUP(C9,Modules!$C$5:$G$36,4,FALSE()),0) -> 0.05 | H9: =IF(D9=1,"Complété",IF(D9=0,"À faire","En cours")) -> En cours
B10: 4 | C10: Facturation fournisseur | D10: =IFERROR(VLOOKUP(C10,Modules!$C$5:$G$36,2,FALSE()),0) -> 1 | E10: =IFERROR(VLOOKUP(C10,Modules!$C$5:$G$36,3,FALSE()),0) -> 0 | F10: =IFERROR(VLOOKUP(C10,Modules!$C$5:$G$36,3,FALSE()),0) -> 0 | G10: =IFERROR(VLOOKUP(C10,Modules!$C$5:$G$36,4,FALSE()),0) -> 0 | H10: =IF(D10=1,"Complété",IF(D10=0,"À faire","En cours")) -> Complété
B11: 5 | C11: Plan comptable | D11: =IFERROR(VLOOKUP(C11,Modules!$C$5:$G$36,2,FALSE()),0) -> 1 | E11: =IFERROR(VLOOKUP(C11,Modules!$C$5:$G$36,3,FALSE()),0) -> 0 | F11: =IFERROR(VLOOKUP(C11,Modules!$C$5:$G$36,3,FALSE()),0) -> 0 | G11: =IFERROR(VLOOKUP(C11,Modules!$C$5:$G$36,4,FALSE()),0) -> 0 | H11: =IF(D11=1,"Complété",IF(D11=0,"À faire","En cours")) -> Complété
B12: 6 | C12: Moteur de comptabilité | D12: =IFERROR(VLOOKUP(C12,Modules!$C$5:$G$36,2,FALSE()),0) -> 1 | E12: =IFERROR(VLOOKUP(C12,Modules!$C$5:$G$36,3,FALSE()),0) -> 0 | F12: =IFERROR(VLOOKUP(C12,Modules!$C$5:$G$36,3,FALSE()),0) -> 0 | G12: =IFERROR(VLOOKUP(C12,Modules!$C$5:$G$36,4,FALSE()),0) -> 0 | H12: =IF(D12=1,"Complété",IF(D12=0,"À faire","En cours")) -> Complété
B13: 7 | C13: Balance de vérification | D13: =IFERROR(VLOOKUP(C13,Modules!$C$5:$G$36,2,FALSE()),0) -> 1 | E13: =IFERROR(VLOOKUP(C13,Modules!$C$5:$G$36,3,FALSE()),0) -> 0 | F13: =IFERROR(VLOOKUP(C13,Modules!$C$5:$G$36,3,FALSE()),0) -> 0 | G13: =IFERROR(VLOOKUP(C13,Modules!$C$5:$G$36,4,FALSE()),0) -> 0 | H13: =IF(D13=1,"Complété",IF(D13=0,"À faire","En cours")) -> Complété
B14: 8 | C14: État des résultats | D14: =IFERROR(VLOOKUP(C14,Modules!$C$5:$G$36,2,FALSE()),0) -> 1 | E14: =IFERROR(VLOOKUP(C14,Modules!$C$5:$G$36,3,FALSE()),0) -> 0 | F14: =IFERROR(VLOOKUP(C14,Modules!$C$5:$G$36,3,FALSE()),0) -> 0 | G14: =IFERROR(VLOOKUP(C14,Modules!$C$5:$G$36,4,FALSE()),0) -> 0 | H14: =IF(D14=1,"Complété",IF(D14=0,"À faire","En cours")) -> Complété
B15: 9 | C15: Bilan | D15: =IFERROR(VLOOKUP(C15,Modules!$C$5:$G$36,2,FALSE()),0) -> 1 | E15: =IFERROR(VLOOKUP(C15,Modules!$C$5:$G$36,3,FALSE()),0) -> 0 | F15: =IFERROR(VLOOKUP(C15,Modules!$C$5:$G$36,3,FALSE()),0) -> 0 | G15: =IFERROR(VLOOKUP(C15,Modules!$C$5:$G$36,4,FALSE()),0) -> 0 | H15: =IF(D15=1,"Complété",IF(D15=0,"À faire","En cours")) -> Complété
B16: 10 | C16: État des flux de trésorerie | D16: =IFERROR(VLOOKUP(C16,Modules!$C$5:$G$36,2,FALSE()),0) -> 1 | E16: =IFERROR(VLOOKUP(C16,Modules!$C$5:$G$36,3,FALSE()),0) -> 0 | F16: =IFERROR(VLOOKUP(C16,Modules!$C$5:$G$36,3,FALSE()),0) -> 0 | G16: =IFERROR(VLOOKUP(C16,Modules!$C$5:$G$36,4,FALSE()),0) -> 0 | H16: =IF(D16=1,"Complété",IF(D16=0,"À faire","En cours")) -> Complété
B17: 11 | C17: État des bénéfices non répartis | D17: =IFERROR(VLOOKUP(C17,Modules!$C$5:$G$36,2,FALSE()),0) -> 1 | E17: =IFERROR(VLOOKUP(C17,Modules!$C$5:$G$36,3,FALSE()),0) -> 0 | F17: =IFERROR(VLOOKUP(C17,Modules!$C$5:$G$36,3,FALSE()),0) -> 0 | G17: =IFERROR(VLOOKUP(C17,Modules!$C$5:$G$36,4,FALSE()),0) -> 0 | H17: =IF(D17=1,"Complété",IF(D17=0,"À faire","En cours")) -> Complété
B18: 12 | C18: Gestion des produits | D18: =IFERROR(VLOOKUP(C18,Modules!$C$5:$G$36,2,FALSE()),0) -> 0.9 | E18: =IFERROR(VLOOKUP(C18,Modules!$C$5:$G$36,3,FALSE()),0) -> 0 | F18: =IFERROR(VLOOKUP(C18,Modules!$C$5:$G$36,3,FALSE()),0) -> 0 | G18: =IFERROR(VLOOKUP(C18,Modules!$C$5:$G$36,4,FALSE()),0) -> 0.1 | H18: =IF(D18=1,"Complété",IF(D18=0,"À faire","En cours")) -> En cours
... B31: 25 | C31: Point de vente (POS) | D31: =IFERROR(VLOOKUP(C31,Modules!$C$5:$G$36,2,FALSE()),0) -> 1 | E31: =IFERROR(VLOOKUP(C31,Modules!$C$5:$G$36,3,FALSE()),0) -> 0 | F31: =IFERROR(VLOOKUP(C31,Modules!$C$5:$G$36,3,FALSE()),0) -> 0 | G31: =IFERROR(VLOOKUP(C31,Modules!$C$5:$G$36,4,FALSE()),0) -> 0 | H31: =IF(D31=1,"Complété",IF(D31=0,"À faire","En cours")) -> Complété
B32: TOTAL Solo TA | D32: =AVERAGE(D7:D31) -> 0.918 | F32: =SUM(F7:F31) -> 0 | G32: =SUM(G7:G31) -> 4.4 | H32: =COUNTA(C7:C31)&" modules" -> 25 modules

Sheet Compagnie
B2: VERSION COMPAGNIE SOLO
B3: Compagnie Solo — Modules inclus
B4: Liste complète des modules de la version compagnie
B6: # | C6: Module | D6: Avancement | E6: PreProd Avancement | F6: Effort | G6: Effort initial | H6: Statut
B7: 1 | C7: Gestion des clients (CRUD) | D7: =IFERROR(VLOOKUP(C7,Modules!$C$5:$G$36,2,FALSE()),0) -> 0.9 | E7: =IFERROR(VLOOKUP(C7,Modules!$C$5:$G$36,3,FALSE()),0) -> 0 | F7: =IFERROR(VLOOKUP(C7,Modules!$C$5:$G$36,3,FALSE()),0) -> 0 | G7: =IFERROR(VLOOKUP(C7,Modules!$C$5:$G$36,4,FALSE()),0) -> 0.05 | H7: =IF(D7=1,"Complété",IF(D7=0,"À faire","En cours")) -> En cours
B8: 2 | C8: Facturation client | D8: =IFERROR(VLOOKUP(C8,Modules!$C$5:$G$36,2,FALSE()),0) -> 1 | E8: =IFERROR(VLOOKUP(C8,Modules!$C$5:$G$36,3,FALSE()),0) -> 0 | F8: =IFERROR(VLOOKUP(C8,Modules!$C$5:$G$36,3,FALSE()),0) -> 0 | G8: =IFERROR(VLOOKUP(C8,Modules!$C$5:$G$36,4,FALSE()),0) -> 0 | H8: =IF(D8=1,"Complété",IF(D8=0,"À faire","En cours")) -> Complété
B9: 3 | C9: Gestion des fournisseurs | D9: =IFERROR(VLOOKUP(C9,Modules!$C$5:$G$36,2,FALSE()),0) -> 0.9 | E9: =IFERROR(VLOOKUP(C9,Modules!$C$5:$G$36,3,FALSE()),0) -> 0 | F9: =IFERROR(VLOOKUP(C9,Modules!$C$5:$G$36,3,FALSE()),0) -> 0 | G9: =IFERROR(VLOOKUP(C9,Modules!$C$5:$G$36,4,FALSE()),0) -> 0.05 | H9: =IF(D9=1,"Complété",IF(D9=0,"À faire","En cours")) -> En cours
B10: 4 | C10: Facturation fournisseur | D10: =IFERROR(VLOOKUP(C10,Modules!$C$5:$G$36,2,FALSE()),0) -> 1 | E10: =IFERROR(VLOOKUP(C10,Modules!$C$5:$G$36,3,FALSE()),0) -> 0 | F10: =IFERROR(VLOOKUP(C10,Modules!$C$5:$G$36,3,FALSE()),0) -> 0 | G10: =IFERROR(VLOOKUP(C10,Modules!$C$5:$G$36,4,FALSE()),0) -> 0 | H10: =IF(D10=1,"Complété",IF(D10=0,"À faire","En cours")) -> Complété
B11: 5 | C11: Plan comptable | D11: =IFERROR(VLOOKUP(C11,Modules!$C$5:$G$36,2,FALSE()),0) -> 1 | E11: =IFERROR(VLOOKUP(C11,Modules!$C$5:$G$36,3,FALSE()),0) -> 0 | F11: =IFERROR(VLOOKUP(C11,Modules!$C$5:$G$36,3,FALSE()),0) -> 0 | G11: =IFERROR(VLOOKUP(C11,Modules!$C$5:$G$36,4,FALSE()),0) -> 0 | H11: =IF(D11=1,"Complété",IF(D11=0,"À faire","En cours")) -> Complété
B12: 6 | C12: Moteur de comptabilité | D12: =IFERROR(VLOOKUP(C12,Modules!$C$5:$G$36,2,FALSE()),0) -> 1 | E12: =IFERROR(VLOOKUP(C12,Modules!$C$5:$G$36,3,FALSE()),0) -> 0 | F12: =IFERROR(VLOOKUP(C12,Modules!$C$5:$G$36,3,FALSE()),0) -> 0 | G12: =IFERROR(VLOOKUP(C12,Modules!$C$5:$G$36,4,FALSE()),0) -> 0 | H12: =IF(D12=1,"Complété",IF(D12=0,"À faire","En cours")) -> Complété
B13: 7 | C13: Balance de vérification | D13: =IFERROR(VLOOKUP(C13,Modules!$C$5:$G$36,2,FALSE()),0) -> 1 | E13: =IFERROR(VLOOKUP(C13,Modules!$C$5:$G$36,3,FALSE()),0) -> 0 | F13: =IFERROR(VLOOKUP(C13,Modules!$C$5:$G$36,3,FALSE()),0) -> 0 | G13: =IFERROR(VLOOKUP(C13,Modules!$C$5:$G$36,4,FALSE()),0) -> 0 | H13: =IF(D13=1,"Complété",IF(D13=0,"À faire","En cours")) -> Complété
B14: 8 | C14: État des résultats | D14: =IFERROR(VLOOKUP(C14,Modules!$C$5:$G$36,2,FALSE()),0) -> 1 | E14: =IFERROR(VLOOKUP(C14,Modules!$C$5:$G$36,3,FALSE()),0) -> 0 | F14: =IFERROR(VLOOKUP(C14,Modules!$C$5:$G$36,3,FALSE()),0) -> 0 | G14: =IFERROR(VLOOKUP(C14,Modules!$C$5:$G$36,4,FALSE()),0) -> 0 | H14: =IF(D14=1,"Complété",IF(D14=0,"À faire","En cours")) -> Complété
B15: 9 | C15: Bilan | D15: =IFERROR(VLOOKUP(C15,Modules!$C$5:$G$36,2,FALSE()),0) -> 1 | E15: =IFERROR(VLOOKUP(C15,Modules!$C$5:$G$36,3,FALSE()),0) -> 0 | F15: =IFERROR(VLOOKUP(C15,Modules!$C$5:$G$36,3,FALSE()),0) -> 0 | G15: =IFERROR(VLOOKUP(C15,Modules!$C$5:$G$36,4,FALSE()),0) -> 0 | H15: =IF(D15=1,"Complété",IF(D15=0,"À faire","En cours")) -> Complété
B16: 10 | C16: État des flux de trésorerie | D16: =IFERROR(VLOOKUP(C16,Modules!$C$5:$G$36,2,FALSE()),0) -> 1 | E16: =IFERROR(VLOOKUP(C16,Modules!$C$5:$G$36,3,FALSE()),0) -> 0 | F16: =IFERROR(VLOOKUP(C16,Modules!$C$5:$G$36,3,FALSE()),0) -> 0 | G16: =IFERROR(VLOOKUP(C16,Modules!$C$5:$G$36,4,FALSE()),0) -> 0 | H16: =IF(D16=1,"Complété",IF(D16=0,"À faire","En cours")) -> Complété
B17: 11 | C17: État des bénéfices non répartis | D17: =IFERROR(VLOOKUP(C17,Modules!$C$5:$G$36,2,FALSE()),0) -> 1 | E17: =IFERROR(VLOOKUP(C17,Modules!$C$5:$G$36,3,FALSE()),0) -> 0 | F17: =IFERROR(VLOOKUP(C17,Modules!$C$5:$G$36,3,FALSE()),0) -> 0 | G17: =IFERROR(VLOOKUP(C17,Modules!$C$5:$G$36,4,FALSE()),0) -> 0 | H17: =IF(D17=1,"Complété",IF(D17=0,"À faire","En cours")) -> Complété
B18: 12 | C18: Gestion des produits | D18: =IFERROR(VLOOKUP(C18,Modules!$C$5:$G$36,2,FALSE()),0) -> 0.9 | E18: =IFERROR(VLOOKUP(C18,Modules!$C$5:$G$36,3,FALSE()),0) -> 0 | F18: =IFERROR(VLOOKUP(C18,Modules!$C$5:$G$36,3,FALSE()),0) -> 0 | G18: =IFERROR(VLOOKUP(C18,Modules!$C$5:$G$36,4,FALSE()),0) -> 0.1 | H18: =IF(D18=1,"Complété",IF(D18=0,"À faire","En cours")) -> En cours
... B38: 32 | C38: Point de vente (POS) | D38: =IFERROR(VLOOKUP(C38,Modules!$C$5:$G$36,2,FALSE()),0) -> 1 | E38: =IFERROR(VLOOKUP(C38,Modules!$C$5:$G$36,3,FALSE()),0) -> 0 | F38: =IFERROR(VLOOKUP(C38,Modules!$C$5:$G$36,3,FALSE()),0) -> 0 | G38: =IFERROR(VLOOKUP(C38,Modules!$C$5:$G$36,4,FALSE()),0) -> 0 | H38: =IF(D38=1,"Complété",IF(D38=0,"À faire","En cours")) -> Complété
B39: TOTAL Compagnie | D39: =AVERAGE(D7:D38) -> 0.775 | F39: =SUM(F7:F38) -> 0 | G39: =SUM(G7:G38) -> 19.475 | H39: =COUNTA(C7:C38)&" modules" -> 32 modules

Sheet Modules
B1: DONNÉES SOURCES
B2: Tous les modules — Vue complète
B3: Inclut les indicateurs de présence dans chaque version
B4: # | C4: Module | D4: Avancement | E4: PreProd Avancement | F4: Effort | G4: Effort initial | H4: Solo TA | I4: Compagnie | J4: Statut
B5: 1 | C5: Gestion des clients (CRUD) | D5: 0.9 | E5: 0 | F5: =G5*(1-D5) -> 0.05 | G5: 0.5 | H5: ✓ Oui | I5: ✓ Oui | J5: =IF(D5=1,"Complété",IF(D5=0,"À faire","En cours")) -> En cours
B6: 2 | C6: Facturation client | D6: 1 | E6: 0 | F6: =G6*(1-D6) -> 0 | G6: 0 | H6: ✓ Oui | I6: ✓ Oui | J6: =IF(D6=1,"Complété",IF(D6=0,"À faire","En cours")) -> Complété
B7: 3 | C7: Gestion des fournisseurs | D7: 0.9 | E7: 0 | F7: =G7*(1-D7) -> 0.05 | G7: 0.5 | H7: ✓ Oui | I7: ✓ Oui | J7: =IF(D7=1,"Complété",IF(D7=0,"À faire","En cours")) -> En cours
B8: 4 | C8: Facturation fournisseur | D8: 1 | E8: 0 | F8: =G8*(1-D8) -> 0 | G8: 0 | H8: ✓ Oui | I8: ✓ Oui | J8: =IF(D8=1,"Complété",IF(D8=0,"À faire","En cours")) -> Complété
B9: 5 | C9: Plan comptable | D9: 1 | E9: 0 | F9: =G9*(1-D9) -> 0 | G9: 0 | H9: ✓ Oui | I9: ✓ Oui | J9: =IF(D9=1,"Complété",IF(D9=0,"À faire","En cours")) -> Complété
B10: 6 | C10: Moteur de comptabilité | D10: 1 | E10: 0 | F10: =G10*(1-D10) -> 0 | G10: 0 | H10: ✓ Oui | I10: ✓ Oui | J10: =IF(D10=1,"Complété",IF(D10=0,"À faire","En cours")) -> Complété
B11: 7 | C11: Balance de vérification | D11: 1 | E11: 0 | F11: =G11*(1-D11) -> 0 | G11: 1 | H11: ✓ Oui | I11: ✓ Oui | J11: =IF(D11=1,"Complété",IF(D11=0,"À faire","En cours")) -> Complété
B12: 8 | C12: État des résultats | D12: 1 | E12: 0 | F12: =G12*(1-D12) -> 0 | G12: 1 | H12: ✓ Oui | I12: ✓ Oui | J12: =IF(D12=1,"Complété",IF(D12=0,"À faire","En cours")) -> Complété
B13: 9 | C13: Bilan | D13: 1 | E13: 0 | F13: =G13*(1-D13) -> 0 | G13: 1 | H13: ✓ Oui | I13: ✓ Oui | J13: =IF(D13=1,"Complété",IF(D13=0,"À faire","En cours")) -> Complété
B14: 10 | C14: État des flux de trésorerie | D14: 1 | E14: 0 | F14: =G14*(1-D14) -> 0 | G14: 1 | H14: ✓ Oui | I14: ✓ Oui | J14: =IF(D14=1,"Complété",IF(D14=0,"À faire","En cours")) -> Complété
B15: 11 | C15: État des bénéfices non répartis | D15: 1 | E15: 0 | F15: =G15*(1-D15) -> 0 | G15: 1 | H15: ✓ Oui | I15: ✓ Oui | J15: =IF(D15=1,"Complété",IF(D15=0,"À faire","En cours")) -> Complété
B16: 12 | C16: Gestion des produits | D16: 0.9 | E16: 0 | F16: =G16*(1-D16) -> 0.1 | G16: 1 | H16: ✓ Oui | I16: ✓ Oui | J16: =IF(D16=1,"Complété",IF(D16=0,"À faire","En cours")) -> En cours
... B36: 32 | C36: Point de vente (POS) | D36: 1 | E36: 0 | F36: =G36*(1-D36) -> 0 | G36: 8 | H36: ✓ Oui | I36: ✓ Oui | J36: =IF(D36=1,"Complété",IF(D36=0,"À faire","En cours")) -> Complété
B37: TOTAL | D37: =AVERAGE(D5:D36) -> 0.775 | F37: =SUM(F5:F36) -> 19.475 | G37: =SUM(G5:G36) -> 58 | H37: =COUNTIF(H5:H36,"✓ Oui") -> 25 | I37: =COUNTIF(I5:I36,"✓ Oui") -> 32 | J37: =COUNTA(C5:C36)&" modules" -> 32 modules

Sheet 1.Identite
A1: Onglet 1 : Identite
A3: Service | B3: Origine | C3: Annee | D3: Marche cible | E3: Doc publique | F3: Sandbox self-serve | G3: Activation prod
A4: Stripe | B4: US -> global | C4: 2010 | D4: Tout, B2B et B2C | E4: docs.stripe.com | F4: OUI | G4: Self-serve 1-3 jours
A5: Helcim | B5: CA Calgary | C5: 2006 | D5: PME canadiennes | E5: devdocs.helcim.com | F5: OUI | G5: Self-serve 1-3 jours
A6: Square | B6: US -> CA | C6: 2009 | D6: Commerce detail | E6: developer.squareup.com | F6: OUI | G6: Self-serve 1-2 jours
A7: PayPal / Braintree | B7: US global | C7: 1998 | D7: Tout | E7: developer.paypal.com | F7: OUI | G7: Self-serve immediat
A8: Moneris | B8: CA Toronto | C8: 2000 | D8: Gros marchand CA | E8: Partielle | F8: NON | G8: Contrat commercial
A9: Nuvei | B9: CA Montreal | C9: 2003 | D9: Enterprise | E9: docs.nuvei.com | F9: A verif | G9: Contrat commercial
A10: Adyen | B10: NL global | C10: 2006 | D10: Enterprise | E10: Partielle | F10: NON | G10: Contrat commercial
A11: Plooto | B11: CA Toronto | C11: 2015 | D11: PME + comptables CA | E11: Partner | F11: NON | G11: Partner 2-4 sem
A12: VoPay | B12: CA Vancouver | C12: 2015 | D12: Devs / fintechs CA | E12: docs.vopay.com | F12: OUI | G12: Sandbox immediat, prod 1 sem
A13: Wise Business | B13: UK -> global | C13: 2011 | D13: International FX | E13: docs.wise.com | F13: OUI | G13: Self-serve
A14: Modern Treasury | B14: US -> CA | C14: 2018 | D14: Bank ops, devs | E14: docs.moderntreasury.com | F14: OUI | G14: Self-serve
A15: Tipalti | B15: US / IL | C15: 2010 | D15: Mass payouts | E15: developer.tipalti.com | F15: A verif | G15: Contrat
... A18: Rotessa | B18: CA Winnipeg | C18: 2015 | D18: PAD seulement | E18: rotessa.com | F18: OUI | G18: Self-serve
A19: Caju Money | B19: CA Toronto | C19: 2020+ | D19: PME canadiennes | E19: A verif | F19: A verif | G19: A verif
A20: Versapay | B20: CA Toronto | C20: 2006 | D20: AR collaboration | E20: Partielle | F20: A verif | G20: Contrat
A21: Bill.com | B21: US California | C21: 2006 | D21: PME US | E21: developer.bill.com | F21: OUI | G21: Self-serve
A22: Routable | B22: US California | C22: 2017 | D22: Bill pay PME | E22: docs.routable.com | F22: OUI | G22: Self-serve
A23: Melio | B23: US / IL | C23: 2018 | D23: Bill pay PME US | E23: Partner | F23: A verif | G23: Partner
A24: Plaid | B24: US -> CA | C24: 2013 | D24: Bank linking | E24: plaid.com/docs | F24: OUI | G24: Self-serve
A25: Flinks | B25: CA Montreal | C25: 2016 | D25: Bank linking CA | E25: docs.flinks.com | F25: OUI | G25: Self-serve
A26: MX | B26: US | C26: 2010 | D26: Bank linking | E26: docs.mx.com | F26: OUI | G26: Self-serve
A27: Currencycloud (Visa) | B27: UK -> global | C27: 2012 | D27: FX B2B API | E27: currencycloud.com/developers | F27: OUI | G27: Self-serve
A28: OFX Business | B28: AU -> global | C28: 1998 | D28: FX | E28: Partner | F28: NON | G28: Contrat
A29: Convera | B29: US global | C29: 2022 | D29: FX corporate | E29: Partner | F29: NON | G29: Contrat

Sheet 2.Encaissement
A1: Service | B1: Cartes credit | C1: Cartes debit | D1: Apple/Google Pay | E1: ACSS Debit (PAD) | F1: Interac Online | G1: EFT pull (B2B) | H1: Bank Pay | I1: Crypto
A2: Stripe | B2: OUI | C2: OUI | D2: OUI | E2: OUI | F2: OUI | G2: OUI | H2: OUI | I2: Partiel
A3: Helcim | B3: OUI | C3: OUI | D3: OUI | E3: OUI | F3: OUI | G3: OUI | H3: OUI | I3: NON
A4: Square | B4: OUI | C4: OUI | D4: OUI | E4: OUI | F4: Partiel | G4: OUI | H4: NON | I4: NON
A5: PayPal | B5: OUI | C5: OUI | D5: OUI | E5: NON | F5: NON | G5: NON | H5: NON | I5: NON
A6: Moneris | B6: OUI | C6: OUI | D6: OUI | E6: OUI | F6: OUI | G6: A verif | H6: NON | I6: NON
A7: Nuvei | B7: OUI | C7: OUI | D7: OUI | E7: A verif | F7: A verif | G7: A verif | H7: NON | I7: OUI
A8: Adyen | B8: OUI | C8: OUI | D8: OUI | E8: A verif | F8: A verif | G8: A verif | H8: OUI | I8: A verif
A9: VoPay | B9: OUI | C9: OUI | D9: OUI | E9: OUI | F9: OUI | G9: OUI | H9: OUI | I9: NON
A10: Plooto | B10: OUI | C10: A verif | D10: NON | E10: OUI | F10: OUI | G10: OUI | H10: NON | I10: NON
A11: Rotessa | B11: NON | C11: NON | D11: NON | E11: OUI | F11: NON | G11: OUI | H11: NON | I11: NON
A12: Bambora | B12: OUI | C12: OUI | D12: OUI | E12: OUI | F12: OUI | G12: A verif | H12: NON | I12: NON
... A14: Lightspeed Payments | B14: OUI | C14: OUI | D14: OUI | E14: NON | F14: NON | G14: NON | H14: NON | I14: NON

Sheet 3.Paiement_OUT
A1: Onglet 3 : Paiement_OUT
A3: Service | B3: EFT CAD | C3: Interac SEND | D3: Interac Request | E3: Cheque imprime | F3: Wire international | G3: Mass batch | H3: Carte virtuelle
A4: Plooto | B4: OUI | C4: OUI | D4: OUI | E4: OUI | F4: OUI | G4: OUI | H4: NON
A5: VoPay | B5: OUI | C5: OUI | D5: OUI | E5: NON | F5: OUI | G5: OUI | H5: NON
A6: Wise Business | B6: OUI | C6: NON | D6: NON | E6: NON | F6: OUI 40+ | G6: OUI | H6: OUI
A7: Modern Treasury | B7: OUI | C7: NON | D7: NON | E7: NON | F7: Via ACH | G7: OUI | H7: NON
A8: Tipalti | B8: OUI | C8: Via partenaire | D8: NON | E8: OUI | F8: OUI 196 pays | G8: OUI | H8: OUI
A9: Trolley | B9: OUI | C9: A verif | D9: NON | E9: OUI US | F9: OUI 210 pays | G9: OUI | H9: NON
A10: Hyperwallet | B10: OUI | C10: OUI reference | D10: NON | E10: A verif | F10: OUI | G10: OUI | H10: OUI
A11: Stripe Connect | B11: OUI Stripe->Stripe | C11: NON | D11: NON | E11: NON | F11: Via Atlas | G11: OUI | H11: OUI
A12: PayPal Payouts | B12: Via Hyperwallet | C12: NON | D12: NON | E12: NON | F12: OUI via PayPal | G12: OUI | H12: NON
A13: Currencycloud | B13: NON | C13: NON | D13: NON | E13: NON | F13: OUI FX | G13: OUI | H13: NON
A14: Bill.com | B14: NON | C14: NON | D14: NON | E14: OUI | F14: NON | G14: NON | H14: NON
... A17: Caju Money | B17: A verif | C17: A verif | D17: A verif | E17: NON | F17: A verif | G17: A verif | H17: NON

Sheet 4.Workflow_B2B
A1: Onglet 4 : Workflow_B2B
A3: Service | B3: Multi-approbation | C3: Multi-compagnie | D3: OCR factures | E3: Tax remittance CRA/RQ | F3: Sync QBO/Xero | G3: Webhook signes | H3: Audit trail
A4: Plooto | B4: OUI 4 niveaux | C4: OUI | D4: OUI | E4: OUI | F4: OUI profond | G4: OUI HMAC | H4: OUI PDF signe
A5: VoPay | B5: NON (vous codez) | C5: OUI | D5: NON | E5: NON | F5: Partiel | G5: OUI HMAC | H5: OUI
A6: Bill.com | B6: OUI | C6: OUI | D6: OUI | E6: NON (US) | F6: OUI US | G6: OUI | H6: OUI
A7: Stripe | B7: NON | C7: OUI Connect | D7: NON | E7: NON | F7: Via apps | G7: OUI HMAC | H7: OUI
A8: Helcim | B8: NON | C8: A verif | D8: NON | E8: NON | F8: OUI basique | G8: OUI | H8: Partiel
A9: Tipalti | B9: OUI | C9: OUI | D9: OUI | E9: NON | F9: OUI | G9: OUI | H9: OUI
A10: Modern Treasury | B10: OUI | C10: OUI | D10: NON | E10: NON | F10: NON | G10: OUI HMAC | H10: OUI
A11: Square | B11: NON | C11: A verif | D11: NON | E11: NON | F11: Partiel | G11: OUI | H11: Partiel
A12: PayPal | B12: NON | C12: A verif | D12: NON | E12: NON | F12: Partiel | G12: OUI | H12: Partiel
A13: Wise Business | B13: OUI basique | C13: OUI | D13: NON | E13: NON | F13: OUI basique | G13: OUI | H13: OUI
A14: Rotessa | B14: NON | C14: A verif | D14: NON | E14: NON | F14: OUI basique | G14: OUI | H14: Partiel
... A16: Routable | B16: OUI | C16: OUI | D16: OUI | E16: NON | F16: OUI US | G16: OUI | H16: OUI

Sheet 5.Tarification
A1: Onglet 5 : Tarification
A3: Service | B3: Abonnement | C3: Carte credit | D3: Interac Send | E3: EFT | F3: Wire intl | G3: Cheque | H3: Setup
A4: Stripe | B4: 0 $ | C4: 2,9 % + 0,30 $ | D4: - | E4: 1,5 % (max 25$) ACSS | F4: - | G4: - | H4: 0 $
A5: Helcim | B5: 0 $ | C5: 1,99 % + 0,08 $ | D5: - | E5: 1 $ | F5: - | G5: - | H5: 0 $
A6: Square | B6: 0 $ | C6: 2,65 % + 0,10 $ | D6: - | E6: - | F6: - | G6: - | H6: 0 $
A7: PayPal | B7: 0 $ | C7: 2,9 % + 0,30 $ | D7: - | E7: - | F7: 4,4 % + frais | G7: - | H7: 0 $
A8: Moneris | B8: ~25 $/mois | C8: negocie ~2,5 % | D8: - | E8: - | F8: - | G8: - | H8: Variable
A9: Plooto | B9: 32-49 $ | C9: 2,9-3,4 % | D9: 1 $ | E9: 0,50 $ | F9: 9,99 $ + 1,5 % | G9: 9,99 $ | H9: 0 $
A10: VoPay | B10: Tier min ~500 $ | C10: - | D10: 0,50-1 $ | E10: 0,25 $ | F10: Variable | G10: - | H10: 0 $
A11: Wise Business | B11: 0 $ | C11: - | D11: - | E11: Inclus FX | F11: Taux IB + 1 % | G11: - | H11: 50 $
A12: Modern Treasury | B12: Negocie | C12: - | D12: - | E12: Negocie | F12: - | G12: - | H12: Contractuel
A13: Tipalti | B13: 149-449 $/mois | C13: - | D13: - | E13: 0,30 $ | F13: 2,50 $/wire | G13: 3 $ | H13: Variable
A14: Trolley | B14: 49 $/mois | C14: - | D14: - | E14: 0,25 $ | F14: - | G14: - | H14: 0 $
... A18: Flinks | B18: Freemium | C18: - | D18: - | E18: - | F18: - | G18: - | H18: -

Sheet 6.Cas_Usage
A1: Onglet 6 : Cas_usage
A3: Service | B3: Ideal pour | C3: A eviter si
A4: Stripe | B4: Encaissement en ligne, cartes + PAD, abonnements recurrents | C4: Vous voulez payer fournisseurs Interac
A5: Helcim | B5: PME canadienne sensible aux frais, POS | C5: Marketplace ou gros volume international
A6: Square | B6: Commerce detail, POS, restos petits | C6: B2B pur, comptabilite avancee
A7: PayPal | B7: Add-on pour clients qui ont deja PayPal | C7: Service primaire B2B Quebec
A8: Moneris | B8: Marchand gros volume avec contrat | C8: PME small/medium, integration rapide
A9: Nuvei | B9: Marketplace, gaming, gros volume | C9: PME standard, time-to-market court
A10: Plooto | B10: App comptable QC avec workflow approbation | C10: Time-to-market urgent, gros volume
A11: VoPay | B11: Fintech qui veut tout faire en API self-serve | C11: Vous voulez workflow approbation built-in
A12: Wise Business | B12: Paiements internationaux multi-devises | C12: Vous restez 100 % CAD domestique
A13: Modern Treasury | B13: Tech-savvy, bank ops avance, EFT CAD | C13: Vous voulez Interac OUT
A14: Tipalti | B14: Marketplace ou agence avec 200+ contractuels | C14: Petit volume (<50 tx/mois)
... A23: Currencycloud | B23: FX programmatique grosse volume | C23: Domestique CAD

Sheet Mes notes Flinks
A3: Produit | B3: Fonctions incluses
A4: Flinks Connect | B4: Widget connexion, multi-institutions, token mgmt, révocation | C4: Plaid Agrégateur US/global Concurrent direct, plus fort hors Canada, moins fort au Canada
A5: Flinks Capital | B5: Comptes, soldes, transactions, identité, catégorisation, intelligence
A6: Flinks IBV | B6: Account verification, identity match, KYC light
A7: Flinks Pay | B7: EFT, PAD, Bill Payment, account-to-account
A8: Flinks Outbound | B8: Partage de données B2B pour banques (non pertinent MngConsul)

Sheet Mes notes Stripe
A2: Stripe peut faire les deux directions : encaisser ET payer
